labelord/__init__.py
labelord/__main__.py
labelord/cli.py
labelord/cli_support.py
labelord/unity.py
labelord/web.py
labelord/web_support.py
labelord/templates/error.html
labelord/templates/header.html
labelord/templates/index.html
labelord/templates/layout.html
labelord_halfdeadpie-0.5.dist-info/DESCRIPTION.rst
labelord_halfdeadpie-0.5.dist-info/METADATA
labelord_halfdeadpie-0.5.dist-info/RECORD
labelord_halfdeadpie-0.5.dist-info/WHEEL
labelord_halfdeadpie-0.5.dist-info/entry_points.txt
labelord_halfdeadpie-0.5.dist-info/metadata.json
labelord_halfdeadpie-0.5.dist-info/top_level.txt
