Metadata-Version: 2.0
Name: labelord-halfdeadpie
Version: 0.5
Summary: Replicate Github Labels
Home-page: https://github.com/HalfDeadPie/labelord_halfdeadpie
Author: Simon Stefunko
Author-email: s.stefunko@gmail.com
License: Public Domain
Keywords: labels,labelord,github,flask,web
Platform: UNKNOWN
Classifier: Intended Audience :: Developers
Classifier: License :: Public Domain
Classifier: Programming Language :: Python
Classifier: Programming Language :: Python :: 3
Classifier: Programming Language :: Python :: 3.6
Classifier: Topic :: Software Development :: Libraries
Classifier: Framework :: Flask
Classifier: Environment :: Console
Classifier: Environment :: Web Environment
Requires-Python: ~=3.6
Requires-Dist: Flask
Requires-Dist: click (>=6)
Requires-Dist: requests
